setup.py
Marshmellow/__init__.py
Marshmellow.egg-info/PKG-INFO
Marshmellow.egg-info/SOURCES.txt
Marshmellow.egg-info/dependency_links.txt
Marshmellow.egg-info/top_level.txt