Metadata-Version: 2.1
Name: Marshmellow
Version: 0.0.1
Summary: A phyton package
Author: marshmellowproject
